gitlab_todotxt/__init__.py
gitlab_todotxt/main.py
gitlab_todotxt/version.py
gitlab_todotxt-0.2.0.dist-info/LICENSE
gitlab_todotxt-0.2.0.dist-info/METADATA
gitlab_todotxt-0.2.0.dist-info/WHEEL
gitlab_todotxt-0.2.0.dist-info/entry_points.txt
gitlab_todotxt-0.2.0.dist-info/top_level.txt
gitlab_todotxt-0.2.0.dist-info/RECORD
