Metadata-Version: 2.1
Name: gitlab-todotxt
Version: 0.2.0
Summary: Synchronise your GitLab issues to a todo.txt file
Home-page: https://github.com/vonshednob/gitlab-todotxt
Author: R
Author-email: contact+gitlab-todotxt@vonshednob.cc
Classifier: Development Status :: 4 - Beta
Classifier: License :: OSI Approved :: MIT License
Classifier: Natural Language :: English
Classifier: Programming Language :: Python :: 3
Requires-Python: >=3.0
License-File: LICENSE
Provides-Extra: xdg
Requires-Dist: pyxdg ; extra == 'xdg'
